platform_utils_eai/__init__.py
platform_utils_eai/functions.py
platform_utils_eai-0.3.0.dist-info/METADATA
platform_utils_eai-0.3.0.dist-info/WHEEL
platform_utils_eai-0.3.0.dist-info/top_level.txt
platform_utils_eai-0.3.0.dist-info/RECORD
