Metadata-Version: 2.1
Name: platform-utils-eai
Version: 0.3.0
Summary: Collection of functions and utilities to create annotated libraries to be uploaded on EAI Platform
Author: Simone Martin Marotta
Requires-Dist: split-folders
